datachunks/__init__.py
datachunks/_chunkingfeeder.py
datachunks/_chunks.py
datachunks-0.0.6.dist-info/LICENSE.txt
datachunks-0.0.6.dist-info/WHEEL
datachunks-0.0.6.dist-info/METADATA
datachunks-0.0.6.dist-info/RECORD
