Metadata-Version: 2.1
Name: datachunks
Version: 0.0.6
Summary: Data chunking for humans, particularly for data engineers
Home-page: https://github.com/amaslyaev/datachunks/
License: MIT
Author: Alexander Maslyeav
Author-email: maslyaev@gmail.com
Requires-Python: >=3.7,<4.0
Classifier: Development Status :: 4 - Beta
Classifier: Intended Audience :: Developers
Classifier: License :: OSI Approved :: MIT License
Classifier: Programming Language :: Python :: 3
Classifier: Programming Language :: Python :: 3.10
Classifier: Programming Language :: Python :: 3.7
Classifier: Programming Language :: Python :: 3.8
Classifier: Programming Language :: Python :: 3.9
Classifier: Topic :: Software Development :: Libraries :: Python Modules
Project-URL: Repository, https://github.com/amaslyaev/datachunks/
